<?xml version="1.0" encoding="UTF-8"?>
<metadata xml:lang="en"><Esri><CreaDate>20151130</CreaDate><CreaTime>10435500</CreaTime><ArcGISFormat>1.0</ArcGISFormat><ArcGISstyle>ISO 19139 Metadata Implementation Specification</ArcGISstyle><SyncOnce>FALSE</SyncOnce><DataProperties><lineage><Process ToolSource="c:\program files (x86)\arcgis\desktop10.2\ArcToolbox\Toolboxes\Data Management Tools.tbx\CalculateField" Date="20151102" Time="081024" Name="" export="">CalculateField GISFormatted2014Truck2toprin_Events d [District] VB #</Process><Process ToolSource="c:\program files (x86)\arcgis\desktop10.2\ArcToolbox\Toolboxes\Data Management Tools.tbx\CalculateField" Date="20151102" Time="081109" Name="" export="">CalculateField GISFormatted2014Truck2toprin_Events District [d] VB #</Process><Process ToolSource="c:\program files (x86)\arcgis\desktop10.2\ArcToolbox\Toolboxes\Data Management Tools.tbx\CalculateField" Date="20151102" Time="081153" Name="" export="">CalculateField GISFormatted2014Truck2toprin_Events R [Route] VB #</Process><Process ToolSource="c:\program files (x86)\arcgis\desktop10.2\ArcToolbox\Toolboxes\Data Management Tools.tbx\CalculateField" Date="20151102" Time="081449" Name="" export="">CalculateField GISFormatted2014Truck2toprin_Events Route [R] VB #</Process><Process ToolSource="c:\program files (x86)\arcgis\desktop10.2\ArcToolbox\Toolboxes\Data Management Tools.tbx\CalculateField" Date="20151102" Time="081553" Name="" export="">CalculateField GISFormatted2014Truck2toprin_Events C [County] VB #</Process><Process ToolSource="c:\program files (x86)\arcgis\desktop10.2\ArcToolbox\Toolboxes\Data Management Tools.tbx\CalculateField" Date="20151102" Time="081630" Name="" export="">CalculateField GISFormatted2014Truck2toprin_Events County [C] VB #</Process><Process ToolSource="c:\program files (x86)\arcgis\desktop10.2\ArcToolbox\Toolboxes\Data Management Tools.tbx\CalculateField" Date="20151102" Time="081908" Name="" export="">CalculateField GISFormatted2014Truck2toprin_Events P [Postmile] VB #</Process><Process ToolSource="c:\program files (x86)\arcgis\desktop10.2\ArcToolbox\Toolboxes\Data Management Tools.tbx\CalculateField" Date="20151102" Time="081944" Name="" export="">CalculateField GISFormatted2014Truck2toprin_Events POSTMILE [P] VB #</Process><Process ToolSource="c:\program files (x86)\arcgis\desktop10.2\ArcToolbox\Toolboxes\Data Management Tools.tbx\CalculateField" Date="20151102" Time="082037" Name="" export="">CalculateField GISFormatted2014Truck2toprin_Events D [Descriptn] VB #</Process><Process ToolSource="c:\program files (x86)\arcgis\desktop10.2\ArcToolbox\Toolboxes\Data Management Tools.tbx\CalculateField" Date="20151102" Time="082135" Name="" export="">CalculateField GISFormatted2014Truck2toprin_Events Descriptn [D] VB #</Process><Process ToolSource="c:\program files (x86)\arcgis\desktop10.2\ArcToolbox\Toolboxes\Data Management Tools.tbx\CalculateField" Date="20151102" Time="082222" Name="" export="">CalculateField GISFormatted2014Truck2toprin_Events l [Leg] VB #</Process><Process ToolSource="c:\program files (x86)\arcgis\desktop10.2\ArcToolbox\Toolboxes\Data Management Tools.tbx\CalculateField" Date="20151102" Time="082257" Name="" export="">CalculateField GISFormatted2014Truck2toprin_Events Leg [l] VB #</Process><Process ToolSource="c:\program files (x86)\arcgis\desktop10.2\ArcToolbox\Toolboxes\Data Management Tools.tbx\CalculateField" Date="20151102" Time="082335" Name="" export="">CalculateField GISFormatted2014Truck2toprin_Events v [Veh_AADT] VB #</Process><Process ToolSource="c:\program files (x86)\arcgis\desktop10.2\ArcToolbox\Toolboxes\Data Management Tools.tbx\CalculateField" Date="20151102" Time="082415" Name="" export="">CalculateField GISFormatted2014Truck2toprin_Events Veh_AADT [v] VB #</Process><Process ToolSource="c:\program files (x86)\arcgis\desktop10.2\ArcToolbox\Toolboxes\Data Management Tools.tbx\CalculateField" Date="20151102" Time="082501" Name="" export="">CalculateField GISFormatted2014Truck2toprin_Events t [Truck_AADT] VB #</Process><Process ToolSource="c:\program files (x86)\arcgis\desktop10.2\ArcToolbox\Toolboxes\Data Management Tools.tbx\CalculateField" Date="20151102" Time="082542" Name="" export="">CalculateField GISFormatted2014Truck2toprin_Events TruckAADT [t] VB #</Process><Process ToolSource="c:\program files (x86)\arcgis\desktop10.2\ArcToolbox\Toolboxes\Data Management Tools.tbx\CalculateField" Date="20151102" Time="082636" Name="" export="">CalculateField GISFormatted2014Truck2toprin_Events t [Trk_Veh_Pc] VB #</Process><Process ToolSource="c:\program files (x86)\arcgis\desktop10.2\ArcToolbox\Toolboxes\Data Management Tools.tbx\CalculateField" Date="20151102" Time="082715" Name="" export="">CalculateField GISFormatted2014Truck2toprin_Events Trk_Veh_Pc [t] VB #</Process><Process ToolSource="c:\program files (x86)\arcgis\desktop10.2\ArcToolbox\Toolboxes\Data Management Tools.tbx\CalculateField" Date="20151102" Time="082856" Name="" export="">CalculateField GISFormatted2014Truck2toprin_Events t [Trk_Veh_Pc] VB #</Process><Process ToolSource="c:\program files (x86)\arcgis\desktop10.2\ArcToolbox\Toolboxes\Data Management Tools.tbx\CalculateField" Date="20151102" Time="082926" Name="" export="">CalculateField GISFormatted2014Truck2toprin_Events Trk_Veh_Pc [t] VB #</Process><Process ToolSource="c:\program files (x86)\arcgis\desktop10.2\ArcToolbox\Toolboxes\Data Management Tools.tbx\CalculateField" Date="20151102" Time="082954" Name="" export="">CalculateField GISFormatted2014Truck2toprin_Events t [TwoAx_Vol] VB #</Process><Process ToolSource="c:\program files (x86)\arcgis\desktop10.2\ArcToolbox\Toolboxes\Data Management Tools.tbx\CalculateField" Date="20151102" Time="083025" Name="" export="">CalculateField GISFormatted2014Truck2toprin_Events TwoAx_Vol [t] VB #</Process><Process ToolSource="c:\program files (x86)\arcgis\desktop10.2\ArcToolbox\Toolboxes\Data Management Tools.tbx\CalculateField" Date="20151102" Time="083055" Name="" export="">CalculateField GISFormatted2014Truck2toprin_Events t [ThreAx_Vol] VB #</Process><Process ToolSource="c:\program files (x86)\arcgis\desktop10.2\ArcToolbox\Toolboxes\Data Management Tools.tbx\CalculateField" Date="20151102" Time="083136" Name="" export="">CalculateField GISFormatted2014Truck2toprin_Events ThreAx_Vol [t] VB #</Process><Process ToolSource="c:\program files (x86)\arcgis\desktop10.2\ArcToolbox\Toolboxes\Data Management Tools.tbx\CalculateField" Date="20151102" Time="083206" Name="" export="">CalculateField GISFormatted2014Truck2toprin_Events f [FourAx_Vol] VB #</Process><Process ToolSource="c:\program files (x86)\arcgis\desktop10.2\ArcToolbox\Toolboxes\Data Management Tools.tbx\CalculateField" Date="20151102" Time="083236" Name="" export="">CalculateField GISFormatted2014Truck2toprin_Events FourAx_Vol [f] VB #</Process><Process ToolSource="c:\program files (x86)\arcgis\desktop10.2\ArcToolbox\Toolboxes\Data Management Tools.tbx\CalculateField" Date="20151102" Time="083306" Name="" export="">CalculateField GISFormatted2014Truck2toprin_Events f [FiveAx_Vol] VB #</Process><Process ToolSource="c:\program files (x86)\arcgis\desktop10.2\ArcToolbox\Toolboxes\Data Management Tools.tbx\CalculateField" Date="20151102" Time="083343" Name="" export="">CalculateField GISFormatted2014Truck2toprin_Events FiveAx_Vol [f] VB #</Process><Process ToolSource="c:\program files (x86)\arcgis\desktop10.2\ArcToolbox\Toolboxes\Data Management Tools.tbx\CalculateField" Date="20151102" Time="083436" Name="" export="">CalculateField GISFormatted2014Truck2toprin_Events t [TwoAx_Pct] VB #</Process><Process ToolSource="c:\program files (x86)\arcgis\desktop10.2\ArcToolbox\Toolboxes\Data Management Tools.tbx\CalculateField" Date="20151102" Time="083508" Name="" export="">CalculateField GISFormatted2014Truck2toprin_Events TwoAx_Pct [t] VB #</Process><Process ToolSource="c:\program files (x86)\arcgis\desktop10.2\ArcToolbox\Toolboxes\Data Management Tools.tbx\CalculateField" Date="20151102" Time="083544" Name="" export="">CalculateField GISFormatted2014Truck2toprin_Events t [ThreAx_Pct] VB #</Process><Process ToolSource="c:\program files (x86)\arcgis\desktop10.2\ArcToolbox\Toolboxes\Data Management Tools.tbx\CalculateField" Date="20151102" Time="083614" Name="" export="">CalculateField GISFormatted2014Truck2toprin_Events ThreAx_Pct [t] VB #</Process><Process ToolSource="c:\program files (x86)\arcgis\desktop10.2\ArcToolbox\Toolboxes\Data Management Tools.tbx\CalculateField" Date="20151102" Time="083649" Name="" export="">CalculateField GISFormatted2014Truck2toprin_Events f [FourAx_Pct] VB #</Process><Process ToolSource="c:\program files (x86)\arcgis\desktop10.2\ArcToolbox\Toolboxes\Data Management Tools.tbx\CalculateField" Date="20151102" Time="083726" Name="" export="">CalculateField GISFormatted2014Truck2toprin_Events FourAx_Pct [f] VB #</Process><Process ToolSource="c:\program files (x86)\arcgis\desktop10.2\ArcToolbox\Toolboxes\Data Management Tools.tbx\CalculateField" Date="20151102" Time="083744" Name="" export="">CalculateField GISFormatted2014Truck2toprin_Events f [FiveAx_Pct] VB #</Process><Process ToolSource="c:\program files (x86)\arcgis\desktop10.2\ArcToolbox\Toolboxes\Data Management Tools.tbx\CalculateField" Date="20151102" Time="083809" Name="" export="">CalculateField GISFormatted2014Truck2toprin_Events FiveAx_Pct [f] VB #</Process><Process ToolSource="c:\program files (x86)\arcgis\desktop10.2\ArcToolbox\Toolboxes\Data Management Tools.tbx\CalculateField" Date="20151102" Time="083908" Name="" export="">CalculateField GISFormatted2014Truck2toprin_Events y [YrVeri_Est] VB #</Process><Process ToolSource="c:\program files (x86)\arcgis\desktop10.2\ArcToolbox\Toolboxes\Data Management Tools.tbx\CalculateField" Date="20151102" Time="083941" Name="" export="">CalculateField GISFormatted2014Truck2toprin_Events YrVeri_Est [y] VB #</Process><Process ToolSource="c:\program files (x86)\arcgis\desktop10.2\ArcToolbox\Toolboxes\Data Management Tools.tbx\CalculateField" Date="20151102" Time="084030" Name="" export="">CalculateField GISFormatted2014Truck2toprin_Events E [EqvAxLd_2W] VB #</Process><Process ToolSource="c:\program files (x86)\arcgis\desktop10.2\ArcToolbox\Toolboxes\Data Management Tools.tbx\CalculateField" Date="20151102" Time="084122" Name="" export="">CalculateField GISFormatted2014Truck2toprin_Events EqvAxLd_2W [E] VB #</Process><Process ToolSource="c:\program files (x86)\arcgis\desktop10.2\ArcToolbox\Toolboxes\Data Management Tools.tbx\CopyFeatures" Date="20151102" Time="084526" Name="" export="">CopyFeatures TruckAADT2014 "N:\Asset Management Branch\GISFiles\AADT\2014 Truck AADT\TruckAADT2014.shp" # 0 0 0</Process></lineage><itemProps><itemName Sync="TRUE">TruckAADT2014</itemName><itemSize Sync="TRUE">0.092</itemSize><itemLocation><linkage Sync="TRUE">file://\\gislibrary\gishq\gisdl\gis\shapes\geo83\Caltrans\Highway\TruckAADT2014.shp</linkage><protocol Sync="TRUE">Local Area Network</protocol></itemLocation><nativeExtBox><westBL Sync="TRUE">-124.264859</westBL><eastBL Sync="TRUE">-114.298927</eastBL><southBL Sync="TRUE">32.549420</southBL><northBL Sync="TRUE">42.005466</northBL><exTypeCode Sync="TRUE">1</exTypeCode></nativeExtBox><imsContentType Sync="TRUE">002</imsContentType></itemProps><coordRef><type Sync="TRUE">Geographic</type><geogcsn Sync="TRUE">GCS_North_American_1983</geogcsn><csUnits Sync="TRUE">Angular Unit: Degree (0.017453)</csUnits><peXml Sync="TRUE">&lt;GeographicCoordinateSystem xsi:type='typens:GeographicCoordinateSystem' xmlns:xsi='http://www.w3.org/2001/XMLSchema-instance' xmlns:xs='http://www.w3.org/2001/XMLSchema' xmlns:typens='http://www.esri.com/schemas/ArcGIS/10.3'&gt;&lt;WKT&gt;GEOGCS[&amp;quot;GCS_North_American_1983&amp;quot;,DATUM[&amp;quot;D_North_American_1983&amp;quot;,SPHEROID[&amp;quot;GRS_1980&amp;quot;,6378137.0,298.257222101]],PRIMEM[&amp;quot;Greenwich&amp;quot;,0.0],UNIT[&amp;quot;Degree&amp;quot;,0.0174532925199433],AUTHORITY[&amp;quot;EPSG&amp;quot;,4269]]&lt;/WKT&gt;&lt;XOrigin&gt;-400&lt;/XOrigin&gt;&lt;YOrigin&gt;-400&lt;/YOrigin&gt;&lt;XYScale&gt;11258999068426.238&lt;/XYScale&gt;&lt;ZOrigin&gt;-100000&lt;/ZOrigin&gt;&lt;ZScale&gt;10000&lt;/ZScale&gt;&lt;MOrigin&gt;-100000&lt;/MOrigin&gt;&lt;MScale&gt;10000&lt;/MScale&gt;&lt;XYTolerance&gt;8.9831528411952133e-009&lt;/XYTolerance&gt;&lt;ZTolerance&gt;0.001&lt;/ZTolerance&gt;&lt;MTolerance&gt;0.001&lt;/MTolerance&gt;&lt;HighPrecision&gt;true&lt;/HighPrecision&gt;&lt;LeftLongitude&gt;-180&lt;/LeftLongitude&gt;&lt;WKID&gt;4269&lt;/WKID&gt;&lt;LatestWKID&gt;4269&lt;/LatestWKID&gt;&lt;/GeographicCoordinateSystem&gt;</peXml></coordRef><copyHistory><copy source="C:\Users\s138325\Desktop\DataReview\TRaffic-OP\2014TruckAADT\TruckAADT2014" dest="\\gislibrary\gishq\gisdl\gis\shapes\geo83\Caltrans\Highway\TruckAADT2014" date="20151130" time="10435500"></copy></copyHistory></DataProperties><SyncDate>20151130</SyncDate><SyncTime>10441100</SyncTime><ModDate>20151130</ModDate><ModTime>10441100</ModTime><scaleRange><minScale>150000000</minScale><maxScale>5000</maxScale></scaleRange><ArcGISProfile>ISO19139</ArcGISProfile></Esri><eainfo><detailed Name="TruckAADT2014" xmlns=""><enttyp><enttypl Sync="TRUE">TruckAADT2014</enttypl><enttypt Sync="TRUE">Feature Class</enttypt><enttypc Sync="TRUE">3434</enttypc><enttypd>A point feature class that represents 2014 truck traffic volumes for the selected locations on the state highway system. </enttypd><enttypds>California Department of Transportation</enttypds></enttyp><attr xmlns=""><attrlabl Sync="TRUE">FID</attrlabl><attalias Sync="TRUE">FID</attalias><attrtype Sync="TRUE">OID</attrtype><attwidth Sync="TRUE">4</attwidth><atprecis Sync="TRUE">0</atprecis><attscale Sync="TRUE">0</attscale><attrdef Sync="TRUE">Internal feature number.</attrdef><attrdefs Sync="TRUE">Esri</attrdefs><attrdomv><udom Sync="TRUE">Sequential unique whole numbers that are automatically generated.</udom></attrdomv></attr><attr xmlns=""><attrlabl Sync="TRUE">Shape</attrlabl><attalias Sync="TRUE">Shape</attalias><attrtype Sync="TRUE">Geometry</attrtype><attwidth Sync="TRUE">0</attwidth><atprecis Sync="TRUE">0</atprecis><attscale Sync="TRUE">0</attscale><attrdef Sync="TRUE">Feature geometry.</attrdef><attrdefs Sync="TRUE">Esri</attrdefs><attrdomv><udom Sync="TRUE">Coordinates defining the features.</udom></attrdomv></attr><attr xmlns=""><attrlabl Sync="TRUE">District</attrlabl><attalias Sync="TRUE">District</attalias><attrtype Sync="TRUE">SmallInteger</attrtype><attwidth Sync="TRUE">4</attwidth><atprecis Sync="TRUE">4</atprecis><attscale Sync="TRUE">0</attscale><attrdef>Caltrans District number</attrdef><attrdefs>State of California, Department of Transportation, Traffic Operations Division</attrdefs><attrdomv><edom xmlns=""><edomv>1, 2, 3, ... 12</edomv><edomvd>Caltrans District number</edomvd><edomvds>California Department of Transportation</edomvds></edom></attrdomv></attr><attr xmlns=""><attrlabl Sync="TRUE">Route</attrlabl><attalias Sync="TRUE">Route</attalias><attrtype Sync="TRUE">String</attrtype><attwidth Sync="TRUE">6</attwidth><atprecis Sync="TRUE">0</atprecis><attscale Sync="TRUE">0</attscale><attrdef>California State Highway System Route</attrdef><attrdefs>State of California, Department of Transportation, Traffic Operations Division</attrdefs><attrdomv><edom xmlns=""><edomv>Route Number</edomv><edomvd>California State Highway System Route</edomvd><edomvds>State of California, Department of Transportation, Traffic Operations Division</edomvds></edom></attrdomv></attr><attr xmlns=""><attrlabl Sync="TRUE">County</attrlabl><attalias Sync="TRUE">County</attalias><attrtype Sync="TRUE">String</attrtype><attwidth Sync="TRUE">3</attwidth><atprecis Sync="TRUE">0</atprecis><attscale Sync="TRUE">0</attscale><attrdef>County Abbreviation</attrdef><attrdefs>State of California, Department of Transportation, Traffic Operations Division</attrdefs><attrdomv><codesetd xmlns=""><codesetn>California County abbreviation</codesetn><codesets>State of California, Department of Transportation, Traffic Operations Division</codesets></codesetd></attrdomv></attr><attr xmlns=""><attrlabl Sync="TRUE">POSTMILE</attrlabl><attalias Sync="TRUE">POSTMILE</attalias><attrtype Sync="TRUE">String</attrtype><attwidth Sync="TRUE">9</attwidth><atprecis Sync="TRUE">0</atprecis><attscale Sync="TRUE">0</attscale><attrdef>The Post Mile is the mileage measured from the county line, or from the beginning of a route. Each postmile along a route in a county is a unique location on the state highway system.</attrdef><attrdefs>Transportation System Network (TSN)</attrdefs><attrdomv><udom>Unique count locations expressed in postmile</udom></attrdomv></attr><attr xmlns=""><attrlabl Sync="TRUE">Descriptn</attrlabl><attalias Sync="TRUE">Descriptn</attalias><attrtype Sync="TRUE">String</attrtype><attwidth Sync="TRUE">60</attwidth><atprecis Sync="TRUE">0</atprecis><attscale Sync="TRUE">0</attscale><attrdef>Count location description</attrdef><attrdefs>California Department of Transportation</attrdefs><attrdomv><udom>Unique location descriptions</udom></attrdomv></attr><attr xmlns=""><attrlabl Sync="TRUE">Leg</attrlabl><attalias Sync="TRUE">Leg</attalias><attrtype Sync="TRUE">String</attrtype><attwidth Sync="TRUE">2</attwidth><atprecis Sync="TRUE">0</atprecis><attscale Sync="TRUE">0</attscale><attrdef>A leg is given for each count location and is denoted by an A, B or O.  According to route direction, B = back leg, A = ahead leg, and O = traffic volume is equal for the back and ahead legs.</attrdef><attrdefs>State of California, Department of Transportation, Traffic Operations Division</attrdefs><attrdomv><edom xmlns=""><edomv>A, B, O</edomv><edomvd>A leg is given for each count location and is denoted by an A, B or O.  According to route direction, B = back leg, A = ahead leg, and O = traffic volume is equal for the back and ahead legs.</edomvd><edomvds>State of California, Department of Transportation, Traffic Operations Division</edomvds></edom></attrdomv></attr><attr xmlns=""><attrlabl Sync="TRUE">Veh_AADT</attrlabl><attalias Sync="TRUE">Veh_AADT</attalias><attrtype Sync="TRUE">Integer</attrtype><attwidth Sync="TRUE">9</attwidth><atprecis Sync="TRUE">9</atprecis><attscale Sync="TRUE">0</attscale><attrdef>Total vehicle AADT</attrdef><attrdefs>California Department of Transportation</attrdefs><attrdomv><udom>Unique values</udom></attrdomv></attr><attr xmlns=""><attrlabl Sync="TRUE">TruckAADT</attrlabl><attalias Sync="TRUE">TruckAADT</attalias><attrtype Sync="TRUE">Integer</attrtype><attwidth Sync="TRUE">9</attwidth><atprecis Sync="TRUE">9</atprecis><attscale Sync="TRUE">0</attscale><attrdef>Annual average daily truck traffic is the total truck traffic volume divided by 365 days.</attrdef><attrdefs>State of California, Department of Transportation, Traffic Operations Division</attrdefs><attrdomv><udom>Unique values</udom></attrdomv></attr><attr xmlns=""><attrlabl Sync="TRUE">Trk_Veh_Pc</attrlabl><attalias Sync="TRUE">Trk_Veh_Pc</attalias><attrtype Sync="TRUE">Single</attrtype><attwidth Sync="TRUE">13</attwidth><atprecis Sync="TRUE">0</atprecis><attscale Sync="TRUE">0</attscale><attrdef>Truck traffic volume as a percentage of total vehicle volume (Annual Average Daily)</attrdef><attrdefs>State of California, Department of Transportation, Traffic Operations Division</attrdefs><attrdomv><udom>Unique values</udom></attrdomv></attr><attr xmlns=""><attrlabl Sync="TRUE">TwoAx_Vol</attrlabl><attalias Sync="TRUE">TwoAx_Vol</attalias><attrtype Sync="TRUE">Integer</attrtype><attwidth Sync="TRUE">9</attwidth><atprecis Sync="TRUE">9</atprecis><attscale Sync="TRUE">0</attscale><attrdef>Annual average daily truck traffic volume for 2 axle vehicle</attrdef><attrdefs>State of California, Department of Transportation, Traffic Operations Division</attrdefs><attrdomv><edom xmlns=""><edomv>Number</edomv><edomvd>Annual average daily truck traffic volume for 2 axle vehicle </edomvd><edomvds>State of California, Department of Transportation, Traffic Operations Division</edomvds></edom></attrdomv></attr><attr xmlns=""><attrlabl Sync="TRUE">ThreAx_Vol</attrlabl><attalias Sync="TRUE">ThreAx_Vol</attalias><attrtype Sync="TRUE">Integer</attrtype><attwidth Sync="TRUE">9</attwidth><atprecis Sync="TRUE">9</atprecis><attscale Sync="TRUE">0</attscale><attrdef>Annual average daily truck traffic volume for 3 axle vehicle</attrdef><attrdefs>State of California, Department of Transportation, Traffic Operations Division</attrdefs><attrdomv><edom xmlns=""><edomv>Number</edomv><edomvd>Annual average daily truck traffic volume for 3 axle vehicle</edomvd><edomvds>State of California, Department of Transportation, Traffic Operations Division</edomvds></edom></attrdomv></attr><attr xmlns=""><attrlabl Sync="TRUE">FourAx_Vol</attrlabl><attalias Sync="TRUE">FourAx_Vol</attalias><attrtype Sync="TRUE">Integer</attrtype><attwidth Sync="TRUE">9</attwidth><atprecis Sync="TRUE">9</atprecis><attscale Sync="TRUE">0</attscale><attrdef>Annual average daily truck traffic volume for 4 axle vehicle</attrdef><attrdefs>State of California, Department of Transportation, Traffic Operations Division</attrdefs><attrdomv><edom xmlns=""><edomv>Number</edomv><edomvd>Annual average daily truck traffic volume for 4 axle vehicle</edomvd><edomvds>State of California, Department of Transportation, Traffic Operations Division</edomvds></edom></attrdomv></attr><attr xmlns=""><attrlabl Sync="TRUE">FiveAx_Vol</attrlabl><attalias Sync="TRUE">FiveAx_Vol</attalias><attrtype Sync="TRUE">Integer</attrtype><attwidth Sync="TRUE">9</attwidth><atprecis Sync="TRUE">9</atprecis><attscale Sync="TRUE">0</attscale><attrdef>Annual average daily truck traffic volume for 5 or more axle vehicle</attrdef><attrdefs>State of California, Department of Transportation, Traffic Operations Division</attrdefs><attrdomv><edom xmlns=""><edomv>Number</edomv><edomvd>Annual average daily truck traffic volume for 5 or more axle vehicle</edomvd><edomvds>State of California, Department of Transportation, Traffic Operations Division</edomvds></edom></attrdomv></attr><attr xmlns=""><attrlabl Sync="TRUE">TwoAx_Pct</attrlabl><attalias Sync="TRUE">TwoAx_Pct</attalias><attrtype Sync="TRUE">Single</attrtype><attwidth Sync="TRUE">13</attwidth><atprecis Sync="TRUE">0</atprecis><attscale Sync="TRUE">0</attscale><attrdef>Percentage of truck traffic volume which are 2 axle trucks (Annual Average Daily)</attrdef><attrdefs>State of California, Department of Transportation, Traffic Operations Division</attrdefs><attrdomv><edom xmlns=""><edomv>Percent</edomv><edomvd>Percent of the annual average daily truck traffic by 2 axle</edomvd><edomvds>State of California, Department of Transportation, Traffic Operations Division</edomvds></edom></attrdomv></attr><attr xmlns=""><attrlabl Sync="TRUE">ThreAx_Pct</attrlabl><attalias Sync="TRUE">ThreAx_Pct</attalias><attrtype Sync="TRUE">Single</attrtype><attwidth Sync="TRUE">13</attwidth><atprecis Sync="TRUE">0</atprecis><attscale Sync="TRUE">0</attscale><attrdef>Percentage of truck traffic volume which are 3 axle trucks (Annual Average Daily)</attrdef><attrdefs>State of California, Department of Transportation, Traffic Operations Division</attrdefs><attrdomv><edom xmlns=""><edomv>Percent</edomv><edomvd>Percent of the annual average daily truck traffic by 3 axle</edomvd><edomvds>State of California, Department of Transportation, Traffic Operations Division</edomvds></edom></attrdomv></attr><attr xmlns=""><attrlabl Sync="TRUE">FourAx_Pct</attrlabl><attalias Sync="TRUE">FourAx_Pct</attalias><attrtype Sync="TRUE">Single</attrtype><attwidth Sync="TRUE">13</attwidth><atprecis Sync="TRUE">0</atprecis><attscale Sync="TRUE">0</attscale><attrdef>Percentage of truck traffic volume which are 4 axle trucks (Annual Average Daily)</attrdef><attrdefs>State of California, Department of Transportation, Traffic Operations Division</attrdefs><attrdomv><edom xmlns=""><edomv>Percent</edomv><edomvd>Percent of the annual average daily truck traffic by 4 axle</edomvd><edomvds>State of California, Department of Transportation, Traffic Operations Division</edomvds></edom></attrdomv></attr><attr xmlns=""><attrlabl Sync="TRUE">FiveAx_Pct</attrlabl><attalias Sync="TRUE">FiveAx_Pct</attalias><attrtype Sync="TRUE">SmallInteger</attrtype><attwidth Sync="TRUE">4</attwidth><atprecis Sync="TRUE">4</atprecis><attscale Sync="TRUE">0</attscale><attrdef>Percentage of truck traffic volume which are 5 or more axle trucks (Annual Average Daily)</attrdef><attrdefs>State of California, Department of Transportation, Traffic Operations Division</attrdefs><attrdomv><edom xmlns=""><edomv>Percent</edomv><edomvd>Percent of the annual average daily truck traffic by 5 axle</edomvd><edomvds>State of California, Department of Transportation, Traffic Operations Division</edomvds></edom></attrdomv></attr><attr xmlns=""><attrlabl Sync="TRUE">YrVeri_Est</attrlabl><attalias Sync="TRUE">YrVeri_Est</attalias><attrtype Sync="TRUE">String</attrtype><attwidth Sync="TRUE">3</attwidth><atprecis Sync="TRUE">0</atprecis><attscale Sync="TRUE">0</attscale><attrdef>Represents the year the truck percentages were verified (counted continuously or quarterly) or estimated.      </attrdef><attrdefs>State of California, Department of Transportation, Traffic Operations Division</attrdefs><attrdomv><edom xmlns=""><edomv>Year and E (Estimate) or V (Verified)</edomv><edomvd>Represents the year the truck percentages were verified (counted continuously or quarterly) or etsimated.  </edomvd><edomvds>State of California, Department of Transportation, Traffic Operations Division</edomvds></edom></attrdomv></attr><attr xmlns=""><attrlabl Sync="TRUE">EqvAxLd_2W</attrlabl><attalias Sync="TRUE">EqvAxLd_2W</attalias><attrtype Sync="TRUE">String</attrtype><attwidth Sync="TRUE">5</attwidth><atprecis Sync="TRUE">0</atprecis><attscale Sync="TRUE">0</attscale><attrdef>Equivalent axle loading are calculated to represent two-way travel</attrdef><attrdefs>State of California, Department of Transportation, Traffic Operations Division</attrdefs><attrdomv><edom xmlns=""><edomv>Number</edomv><edomvd>Equivalent axle loading are calculated to represent two-way travel</edomvd><edomvds>State of California, Department of Transportation, Traffic Operations Division</edomvds></edom></attrdomv></attr></detailed></eainfo><mdLang><languageCode value="eng"/><countryCode value="USA" Sync="TRUE"/></mdLang><mdChar><CharSetCd value="004"/></mdChar><mdHrLv><ScopeCd value="005"/></mdHrLv><mdHrLvName Sync="TRUE">dataset</mdHrLvName><mdContact xmlns=""><rpIndName>Shiriedel Acayan</rpIndName><rpOrgName>California Department of Transportation</rpOrgName><rpPosName>Transportation Planner (GIS)</rpPosName><rpCntInfo><cntPhone><voiceNum>916-651-9377</voiceNum></cntPhone><cntAddress><delPoint>1120 N St, MS 36</delPoint><city>Sacramento</city><adminArea>CA</adminArea><postCode>95814</postCode><eMailAdd>shiriedel.acayan@dot.ca.gov</eMailAdd></cntAddress></rpCntInfo><role><RoleCd value="010"/></role></mdContact><mdDateSt Sync="TRUE">20151130</mdDateSt><mdStanName>ArcGIS Metadata</mdStanName><mdStanVer>1.0</mdStanVer><distInfo><distFormat><formatName Sync="TRUE">Shapefile</formatName><formatVer>ArcGIS 10.2</formatVer></distFormat><distFormat><formatName Sync="TRUE">Shapefile</formatName><formatVer>10.2</formatVer></distFormat><distTranOps><transSize>0.26</transSize></distTranOps></distInfo><dataIdInfo><idCitation xmlns=""><resTitle Sync="FALSE">Truck Traffic Volumes (2014)</resTitle><date><pubDate>2015-11-30T00:00:00</pubDate><createDate>2015-11-02T00:00:00</createDate></date><citRespParty><rpIndName>Binoy Alexander</rpIndName><rpOrgName>California Department of Transportation</rpOrgName><rpPosName>Research Analyst II</rpPosName><rpCntInfo><cntPhone><voiceNum>916-654-6939</voiceNum></cntPhone><cntAddress><delPoint>1120 N St, MS 36</delPoint><city>Sacramento</city><adminArea>CA</adminArea><postCode>95814</postCode><country>US</country><eMailAdd>binoy.alexander@dot.ca.gov</eMailAdd></cntAddress></rpCntInfo><role><RoleCd value="001"/></role></citRespParty><presForm xmlns=""><PresFormCd value="005"/></presForm></idCitation><idAbs>&lt;DIV STYLE="text-align:Left;"&gt;&lt;DIV&gt;&lt;DIV&gt;&lt;P&gt;&lt;SPAN&gt;Annual average daily truck traffic is the total truck traffic volume divided by 365 days. Truck counting is done throughout the state in a program of continuous truck count sampling. The sampling includes a partial day, 24-hour, 7-day and continuous vehicle classification counts. The partial day and 24-hour counts are usually made on high volume, urban highways. The 7-day counts are made on low volume, rural highways. The counts are usually taken only once in the year. About one-sixth of the locations are counted annually. The resulting counts are adjusted to an estimate of annual average daily truck traffic by compensating for seasonal influence, weekly variation, and other variables that may be present. Annual average daily truck traffic is necessary for presenting a statewide picture of truck flow, evaluating truck trends, planning and designing highways and for other purposes. Truck traffic is classified by number of axles. The two-axle class includes 11/2-ton trucks with dual rear tires and excludes pickups and vans with only four tires. Total vehicle AADT for the same year is taken from the Traffic Volumes on California State Highways booklet also published by the California Department of Transportation.Reference Link: http://www.dot.ca.gov/hq/traffops/saferesr/trafdata/index.htm&lt;/SPAN&gt;&lt;/P&gt;&lt;/DIV&gt;&lt;/DIV&gt;&lt;/DIV&gt;</idAbs><idPurp>Truck Annual Average Daily Traffic (AADT) is shown for selected locations on the California State Highway System. The truck traffic volumes data are summarized annually and published by Caltrans, Traffic Operations Division.</idPurp><idCredit>California Department of Transportation</idCredit><idPoC xmlns=""><rpIndName>Shiriedel Acayan</rpIndName><rpOrgName>California Department of Transportation</rpOrgName><rpPosName>Transportation Planner (GIS)</rpPosName><rpCntInfo xmlns=""><cntPhone><voiceNum tddtty="">916-651-9377</voiceNum></cntPhone><cntAddress addressType=""><delPoint>1120 N St, MS 36</delPoint><city>Sacramento</city><adminArea>CA</adminArea><postCode>95814</postCode><eMailAdd>shiriedel.acayan@dot.ca.gov</eMailAdd></cntAddress></rpCntInfo><role><RoleCd value="010"/></role></idPoC><resMaint><maintFreq><MaintFreqCd value="009"/></maintFreq></resMaint><otherKeys><keyword>AADT</keyword><keyword>Truck traffic</keyword></otherKeys><searchKeys><keyword>AADT</keyword><keyword>Truck traffic</keyword></searchKeys><resConst><Consts><useLimit>&lt;DIV STYLE="text-align:Left;"&gt;&lt;DIV&gt;&lt;DIV&gt;&lt;P&gt;&lt;SPAN&gt;This is Category I data. Category I data are public domain and available to share with Caltrans partners.&lt;/SPAN&gt;&lt;/P&gt;&lt;/DIV&gt;&lt;/DIV&gt;&lt;/DIV&gt;</useLimit></Consts></resConst><spatRpType><SpatRepTypCd value="001"/></spatRpType><dataLang><languageCode value="eng"/><countryCode value="USA" Sync="TRUE"/></dataLang><dataChar><CharSetCd value="004"/></dataChar><envirDesc Sync="TRUE">Microsoft Windows 7 Version 6.1 (Build 7601) Service Pack 1; Esri ArcGIS 10.3.1.4959</envirDesc><dataExt xmlns=""><geoEle><GeoBndBox><exTypeCode>true</exTypeCode><westBL>-124.264859</westBL><eastBL>-114.298927</eastBL><southBL>32.549683</southBL><northBL>42.005472</northBL></GeoBndBox></geoEle></dataExt><dataExt xmlns=""><geoEle><GeoBndBox><exTypeCode>true</exTypeCode><westBL>-124.264859</westBL><eastBL>-114.298927</eastBL><southBL>32.548801</southBL><northBL>42.005468</northBL></GeoBndBox></geoEle></dataExt><dataExt xmlns=""><geoEle><GeoBndBox><exTypeCode>true</exTypeCode><westBL>-124.264859</westBL><eastBL>-114.298927</eastBL><southBL>32.548801</southBL><northBL>42.005468</northBL></GeoBndBox></geoEle></dataExt><dataExt xmlns=""><geoEle><GeoBndBox><exTypeCode>true</exTypeCode><westBL>-124.264859</westBL><eastBL>-114.298927</eastBL><southBL>32.548801</southBL><northBL>42.005468</northBL></GeoBndBox></geoEle></dataExt><dataExt xmlns=""><geoEle xmlns=""><GeoBndBox esriExtentType="search"><exTypeCode Sync="TRUE">1</exTypeCode><westBL Sync="TRUE">-124.264859</westBL><eastBL Sync="TRUE">-114.298927</eastBL><northBL Sync="TRUE">42.005466</northBL><southBL Sync="TRUE">32.549420</southBL></GeoBndBox></geoEle></dataExt><tpCat><TopicCatCd value="018"/></tpCat></dataIdInfo><mdMaint xmlns=""><maintFreq><MaintFreqCd value="009"/></maintFreq></mdMaint><dqInfo><dqScope><scpLvl><ScopeCd value="005"/></scpLvl></dqScope><dataLineage><statement>The truck traffic volumes data used to create this GIS file are from Caltrans Traffic Census database compiled by Caltrans Traffic Data Branch summarized annually.</statement></dataLineage></dqInfo><spatRepInfo><VectSpatRep><geometObjs Name="TruckAADT2014"><geoObjTyp><GeoObjTypCd value="004" Sync="TRUE"></GeoObjTypCd></geoObjTyp><geoObjCnt Sync="TRUE">3434</geoObjCnt></geometObjs><topLvl><TopoLevCd value="001" Sync="TRUE"></TopoLevCd></topLvl></VectSpatRep></spatRepInfo><refSysInfo><RefSystem><refSysID><identCode code="4269"/><idCodeSpace Sync="TRUE">EPSG</idCodeSpace><idVersion Sync="TRUE">8.6.2</idVersion></refSysID></RefSystem></refSysInfo><spdoinfo><ptvctinf><esriterm Name="TruckAADT2014"><efeatyp Sync="TRUE">Simple</efeatyp><efeageom code="1" Sync="TRUE"></efeageom><esritopo Sync="TRUE">FALSE</esritopo><efeacnt Sync="TRUE">3434</efeacnt><spindex Sync="TRUE">TRUE</spindex><linrefer Sync="TRUE">FALSE</linrefer></esriterm></ptvctinf></spdoinfo><Binary><Thumbnail><Data EsriPropertyType="PictureX">/9j/4AAQSkZJRgABAQEAYABgAAD/2wBDAAMCAgMCAgMDAwMEAwMEBQgFBQQEBQoHBwYIDAoMDAsK
CwsNDhIQDQ4RDgsLEBYQERMUFRUVDA8XGBYUGBIUFRT/2wBDAQMEBAUEBQkFBQkUDQsNFBQUFBQU
FBQUFBQUFBQUFBQUFBQUFBQUFBQUFBQUFBQUFBQUFBQUFBQUFBQUFBQUFBT/wAARCACgAPADASIA
AhEBAxEB/8QAHwAAAQUBAQEBAQEAAAAAAAAAAAECAwQFBgcICQoL/8QAtRAAAgEDAwIEAwUFBAQA
AAF9AQIDAAQRBRIhMUEGE1FhByJxFDKBkaEII0KxwRVS0fAkM2JyggkKFhcYGRolJicoKSo0NTY3
ODk6Q0RFRkdISUpTVFVWV1hZWmNkZWZnaGlqc3R1dnd4eXqDhIWGh4iJipKTlJWWl5iZmqKjpKWm
p6ipqrKztLW2t7i5usLDxMXGx8jJytLT1NXW19jZ2uHi4+Tl5ufo6erx8vP09fb3+Pn6/8QAHwEA
AwEBAQEBAQEBAQAAAAAAAAECAwQFBgcICQoL/8QAtREAAgECBAQDBAcFBAQAAQJ3AAECAxEEBSEx
BhJBUQdhcRMiMoEIFEKRobHBCSMzUvAVYnLRChYkNOEl8RcYGRomJygpKjU2Nzg5OkNERUZHSElK
U1RVVldYWVpjZGVmZ2hpanN0dXZ3eHl6goOEhYaHiImKkpOUlZaXmJmaoqOkpaanqKmqsrO0tba3
uLm6wsPExcbHyMnK0tPU1dbX2Nna4uPk5ebn6Onq8vP09fb3+Pn6/9oADAMBAAIRAxEAPwD9OKKK
K9A8QKKKKACiiigArlPiZ8VPCvwd8MnxB4v1dNI0zzkt0fypJpZpWyRHHFGrSSNhWYqikhUdjhVY
jq6+Vv8Ago58N/FPxC/Z/uJPD406707RZTqmsadfCKOWW1jQs8kFzIR5DqodXIZd0Ms4+Y4R4m3G
LaHufRcXj7wxPceHYI/EekyT+IoWuNFjW+iLapEsYlaS2G7MyiNlclMgKQehrer8i/il8P8A4c/D
f9lL4W+KfAfioXHjuy1GWxl1TSopbe3iaO5mvgbhbhY5Y5LWS4iWCSTyWm86BnUxsoTm/i94l+OH
7N3gWEfE2/8AEviXSPiT4ZvUh0vUPE2oSrpsc0G0CZZWEkd1bPdW6yRuhhkVimS+Xj4o4u+6NfZu
/wDX9fmfsJ4Z8VaL420O21rw7rFhr2j3W7yNQ0y5S5t5drFG2yISrYZWU4PBUjtWDH8aPh9Nb+HZ
4/HfhmSDxHM1vosi6vbldUlWQRNHbHf++YSMqEJkhmA6mvxM+GHxyuofAfxX+Hugza7f6p4yk0+H
SLSx1q6EBUq0V9EkLAm4ublPIt1RoiSMkMPLRX+1PEH/AASXv5vhDZTaZ4zhl+MU5/4nl/dExaVf
28gjWSzjAiZoViVMpMIyzsZN6gOghl4zltdWHGlKaul0+7yP0RrL0/xVoura5q2jWOr2F5rGk+V/
aOn29yklxZ+apeLzowd0e9QWXcBuAyM1478HNb+F/jDwHeyQ/FC/8W3HhG1SDxH4ifxDqNhDI8cW
ZL4qbgItvIY5ZFljLQkK+x2CHHz5qvi39ln4Yax478X+FPH+uy+Mtaj1Cz06OxudTnEN2QJpXheG
PfLFcThJRNNJLFIYn8ltqSAH11XsolSo8qTuj75oqrpeqWWu6XZ6lpt5b6hp15ClxbXlrKssM8Tq
GSRHUkMrKQQQcEEEVar0jmCiiigAooooAKKKKACiiigAooooAKKKKACiiigAooooAKKKKACiiigA
rwv9uTXR4d/ZP+I902oNpqSWCWbusKSees80cLWx3kCNZhIYTLnMQlMgyUAr3Svzx/4KzfE661TQ
9B+DmmRalZ3mpCPX57yKZY7e+jjMyR2W3cPM+dDM5b5Y/JgIDs67ca0lGDch6LWTsjyr9lHX/FXw
41SztNO1Jj4a8R6Lc+KdF1FSkCi/sNNuUvHj84vFdyrPJNaToiCWRIYLlSkKjd9X/wDBRb4Q6L8a
f2c7Px48un2t/wCFoG1W1XUZ0K3ltPGgksY5EZ4xNM4t/LdA5aSNI0ZRMXHnHwo/ZB+Cvj74I/DT
4naFqGv67Nf32mHVLy8b7H/bM39ow28i3NuN3keQ4lRFt3UfKN0k4w7fOv7Xv7Zk3xm+KWl2Xw1v
dRX4P+GtHQX+jXFmq6TdJ9r8prieKGUOkJQ2ghMhjnhl8vylgmZXrwFHmfod8YuFJxn+f/ATPLvg
DeePYv2rvAmn+A9Q0O8+ITXRv7ZrW0gg09luLBp5IrtVIWMW8UssEkEKBoQk0cJ3qlfb/wANP+Cj
998IF8SeDfj7pesTeM9FeV7b7Ha2w1C6VGUyRXESGOBGVGaaKVGEc0C5B3hTP8E/s8+Ol+Fv7SFx
rninWtf8B6FcT6x4c1mx8PzXMOraRBcQXClxFI8kypbTOkx3tK6Pb7sSSKM39Tsfht8G/iV4c1PR
PF1h8YvClvfyX2oaLq3hqXQ7Ca5V0IsMSTGbHCsxkTyEKw7xMC8Y0nBNq5nf2dnF+v8Awx6d480X
4H/H741T6V4I8C+KPD9vNomo3Evhu1mgfUb3ULa1uL+G3sYg1wtlC6oY90QlUkxxJbx4Mh9q/ZV/
Z7+G3xc/Yt1nxVrvhG5udd0B9XbTvFIu72xbU9kAdJ40R4wIYiWtljG6NWgmK7WllFfUfw3+O/7N
Gg3kMunzeDfhhr+n6ZHYyWer2drod1YRTMbmXT97BULRzs/nwRO4im3CQB+uXBq3xj164+Nup+Jb
zQdR+EV54cvLnwveaXLDLHPE8Ja1ktXjJdlaAsZ2nODKUMH7rNZJvRM1jTSs5O9+y0/4G3c+jdL0
uy0LS7PTdNs7fT9Os4Ut7aztYlihgiRQqRoigBVVQAABgAACrVFFfSrY88KKKKYgooooAKKKKACi
iigAooooAKKKKACiiigAooooAKKKKACiiigArxP4+fCbw74/uCvjrwzZ+LvAGpR2dtqkMkjwXGlS
QSzPDfxzK6lY1+0yrKVZWWMk5ZDIp9sorOpBVIuLLhLkdz8oP2HfjQ3hfxvqnw2tNStb34b6pqkW
r2GuXUcdklxNYajZK19+9kVreOa1h5t3B2GKFY8Fnz7HP/wTn+EGt/EzR9R+Hfxkk0qUXLTDSYr6
21C4t0UxNH/ZsqOkltLFHCQszidhtRmyUO75C8eeBvDfwX1J/F/wz+MVnc6/aeINZ0OyvFvY7e++
yXFmohvg7Q+ZMhRr5HvEOwyvD9nKD5x9kaf8L/Fnwf8A2SPAfjH4VeJ7zUNQkt7jXLZ7zQ4yun2d
9axXDLb25NwlmRHb45ZozPdSM8iRuwrwJLldkzrpWa5Gr2/K+i/rsfCn7XvwG174E/H7Xm8X6nZe
J9c1G1bxG8mkxzxnVYbi5uI57icKFW1kYpI7RpuiUOqgsAc9l8fvgz4T+FnxN0HTfhZ4sm8Uapaa
Tpl5d6hvePzdUSOG6STS7wSsYzcxyG9YlvLjBby5ndlgXR/b88E+OJPE3wwvfHWrtr/xduvD6rqF
jbiG2OlQrc3slmfNiVYZHkBk8wJnZJaSbX2SxY+V/COsaHqWoWLakscAsyZ7q4vVWdY4CT5sNta7
445G3O8qJujG47dwxvN7q97mNS15Ja7fL+u57h8EfgnH8Y/2j9N+FfxGvtVh8aS3GrRz37XrXgTV
Ixczyy3Kyqy3CLLavHIsUi+aZdwm+U5+g/h98Ndc/YF1STwV4jgvPFOseOfC19Z3H/CMo8enR7nm
2yjeu7UJLdUV5WKwfZIJ5GxMJOOy0j4Tv8ctW1DxZ8HtdluPif4c0gaJrfiO91zeupXUFulnDf2k
4AnMl3aJcRLclRAN7yR/vkMtfnhpdxqlh4o1TSrPSY9KvdORfP065zZ3Nhcw3IRfNhK+ZcywO/zR
ojuUQu6fu32rVvQpp017qvre9/v/ADZ/RXRVXS9Ustd0uz1LTby31DTryFLi2vLWVZYZ4nUMkiOp
IZWUggg4IIIq1X0BzBRRRTEFFFFABRRRQAUUUUAFFFFABRRRQAUUUUAFFFFABRRRQAUUUUAFFFFA
H4zftYfA24+DvxK+IEmj3Oh3th9rnltrG3vfs0ukW86eZbyS2yyK9tbxNerb28sR8lpYgkoAlWFu
O8LftW/GLwX8O7XwTZeOb7XfA+n2jKmm3MEMUs2mLGG2B3iE6xBmEanziAi7BGyKUr72/bR/ZT8S
ah4gl+MXwqvtTtPGlrtn1Cx024kW4kZYVtxeWuz52lSBfLa2B2zoMKPMys35c/Fb4iaP4u8fT61P
pVjYQ6tdxaiIlmublbaZihu7qRZsyyLdSK8wjkkdkSQKGIAJ8KpTlTqOyFFyhK9Prv1v5/Ltfba+
iPc/2oP2ndf/AG2/D+gRy+HdKFt4bgn1BoNGkiW6kbJW4cyzjzYoljCSeXGG3R2808qhYwbfwL9m
fxZpXwd/aX+HHia/Onatplhr0QvIr2ykuxbQGTymuBHGDuljVzNEYjIRJGhG4gA9na+NvBtl8M59
CsPDVvH4vu7xGt9XEm6NLdruK5Nx5L4W0dFtnCSLHMxgumSRlVU8zyiX7LrFzrd1qlxM1jp9yvnL
pqb/ALWXmkxK0oUJuXedpKqGHyjbUxfKrdDpjWlF8zd/z7LT+vuPZ/2cNFi+OHxw8K6Xf6qvhKPx
Nb3mn3epQ24jhtJngnWBEXEcaQ3MxNsbSEojxyNCu0uNvdftsfs/+Lv2b/FljYX+sax400XUNHVN
Evpr8qlpFZQxmSNE3FraOCeaRo7cboxHPCA7SK1fMi6i3ii7n0qW4mE+rPZpLfzF/s1irNGWleO2
Vy6+ZK5KrGXBPAaRiK+u/jZJ8Db79nDwp8N9I+IGo+NLvTdav9en1rSPD/lXGgwrGI5bWDT7uSFo
beVtjvGLgFplaXDAhVjl112JhBOLU9PO/p/XTY/Uv4C6vouufBXwPc+HdfsPFOjro9rbwaxplmll
b3PlRiNmW2QBbf5kYGAAeUQUwCuB3lflp+xLcfEb9kG+0Cw8TXtnH8IfFMd54jiumms2S/tFtLdm
1G0j3C8yi/Z5HSRBtthM7Qo6nb+kHwz+KnhX4xeGR4g8Iaumr6Z5z27v5UkMsMq4JjkikVZI2wys
FdQSrowyrKT7dOpGa0JnHlkdXRRRW5mFFFFABRRRQAUUUUAFFFFABRRRQAUUUUAFFFFABRRRQAUU
UUAFFFFABX4r/wDBSf4E2vgn9o3xRrumwatpGkeJIY9SdVsGaC7uNyNfNE4bDIpeGZi+B5krLxtB
r9qK8Q/bU8IzeNP2ZPHtlY+Bbf4ha2mmzNpmlSRRyTQ3DxtF9qtw6sfPhjlkkQIN7ldiEM4rGrFz
jozSDd7J2Pw1ydF028iiu1injljjXUdPUNaqqxRlzBJ8uLhlU7huUOMjrtrF8VadJpt9feHIdOt7
C5t7zzLmC+ja2vLGYN5b2chm2n92+QRj+EscYYCndat+806wtwsMUDeW1j9pR4TcKMCdmZfLZWZu
5bhSNwXbj234dfAW48deF/DB+HfiOw1Tx5Jdy2t74euLePStQ0+RLmQQ7JLmQRXZkidi6qyiMm3j
Zizor+Qo8uvU0jTlH3t2eb33iS78SLJE1yyvAXvLqRLmNFt5UcRxTtKqfOQpRdsQ+bClTuYgdp8C
fhj4v+Ovja28H+ELWPUL+ScXiWmsQGSGRWULNf3jjJhiVJUYHkMSip5khG7hoPDfltFA9tpHiTT9
LkmSCTS5ZEk1lXY4dDtEh2ja+10R1VhuVScV6p8J/iJqPwd+weLfBfi618Na5ayxab9k0ZEkneH7
I4vWla6lkjEAnFo+JF8qWa6ZoNptyqZNRScUtjC1OKcEtF2t/X5b6O6PuD/goZ+zTceHfgtpXxA1
XxJdeIbzwn4Y0zQNSv7wZOozwXC+VcXMb+Y0izSzSIyrIrK06uzSKrAcd+xB4N8c+LYdG1j4deL4
dIsfB+tMvinwut7NbS6kjlZxcCxceWxntpPsEYnKLF/Z6yRybiRHe/Ya+NnxG/aO1jxl8LvGmuXN
3aeKNK/ty+uNTmW9dLFm8m9S3RlKRC5+0QIsI/dQrHMVjUsN1H4I/Alv2a7zUdd8X+P9F8Qfs769
pd9ouoa94Wu2vLXWrPyblFtp4YAGidWE8vnQGV42LQiRg8jhRbjqt/6/yOxwjUkqkVo99vLX8Pu3
PuL4B/tPeCP2kV8Qt4OlvXXRp0SQ3luI/tEEhkENzHhj+7kMMwCvtlUxnfGmRn1qvyv0X44eE/BH
w58ZQfs93Hj3w7458NRJrnipvEVpa3l5qulFlje4ijiE1oHtme0DEpEFgaZvnYOw+5P2Sf2il/aQ
+F663dWlrYa9p832LU4rGbzLWWUIrefbEncYXyQN3KvHKmX8ve3r0K/tElLc5Gno+6vpt957ZRRR
XYSFFFFABRRRQAUUUUAFFFFABRRRQAUUUUAFFFFABRRRQAUUUUAFFFFAH4t/8FAv2af+FC/ErUvE
MXhu10/wbrzsNJ1bSXuIYonLM8llIuZEimMbvFGirHD5MCFQWEyr5L8Dfi14i+B1tc6mN+j3jSw2
6X91bCXyJ4nhuIWlViZXTbEF8hBHGzC3kcuYEWv09/4Knap4k079mOCHQo5pdNvdfs7bXkjZY420
/ZM5SWYj9yjTJbpvyuSypk79rfm3qH7OfivS/hxZfGSz1LTrrTbyf7I99Y3c07eH7gjJt9WW5iV4
nKSJGjKGRj5Z3YliaTxsRH2cml/X9ehcpSUW4vX+l8vua62OP8VfDDxr8HvAlnbeINNn0hPEenI+
mzvcWE1ncg3RExjlVm2SqqxpJtYTIrskm2KTa2z4B8c6n8PvF2na0LGxvru1vJ5Uh1aa0+3iPfFO
Y7aMpK1rdt5sTxXaxqwkDqhYROtfaf7C/wAWtL1vwYt5p9hbWvjPwJplxd2K3enRRR654fgSOOYS
SRAiO8hd2QTbUZ0eIN52ZWX5e1ib9nTRvGHiaAeHviV4Uvft81teaMNb0+JbLSsgNEFnsmkF8mAh
tWZuVO67L7jXP8TujSUFJe0i/wDgPb/O6MP4ceMrqO/1jwdomuaTps/jS7bTPEWr63cRaPH9nC+Z
MGu5JvMtYJmdjcRpEPMNjbxr5nmmIfpF/wAKF+DUnwz1n9lBviBHN8SNTii1+9v5rVJZzqSrG8c4
iYGBD5dsn+iK4kNsrMSdzzH8crLUdc0XxRIseoss0spAuo7Jm865jhZQm1kDFyZdjZGcybjnrX13
/wAE4fHUdn+0N4a0nwj4J/4TO9R5Qb3UlzNoumylEuZ4nULHbyIWd3kfzfORo7eMwvI3mzKLVn+P
9f19xVK8Jxur6LXX56Wtq/Tz2R9s/sI/sep+y7498eW0niu81S9hhgtPscdrJbW17BIFkjvZdzFZ
X3RzRxqv+p/0hSZDJvr6k8XeAotd1C21vTJotI8U2iCC31UxNKPIMivJDLEroJY2CsAGPyFiy7W5
r5e/4KDXniL4beE7zxN4X8RyeFYtdW3trxtLWS3vNRurVZ5YLVbmBvOjaVHc70Q/8ecaSMkMkjL6
9+xv8a9T+PHwI0XxBrVpOms2v/EsvdSKr9m1WeJEEl5bMqorRuxIIVVCSJLGMiPccHKSaqJnenHm
dK3md54b8WHWtS1TSbzTrjSdZ0vyvtNvMN0TrIDsmglHEkTFJAGwrZRgyIeK6Cvn79obVviBefHf
4W+HfD/gO5v/AA7LOLifxhYFhc2DFys4WbBitkjhCyMlwjrdh/KjAkTcOC+Fv7c8mqfH7x/4I+IP
/CO+EvDWhG9hsvEF1eLZRyTWV5HZzB2llZW855PMRfkMQXZmfPmD2qGKjUSU9zz6sFGVl6fhfTuf
X1FFFegc4UUUUAFFFFABRRRQAUUUUAFFFFABRRRQAUUUUAFFFFABRRRQBQ8QaDp/irQdS0TVrVL7
StStpLO7tZM7ZoZEKOhx2KsR+NfJvg/4N+J/hv8AHS/+EsCaWv7Pni3TNRZ9LvLhPtF2klsqXEf2
gYvJLxZHVQzyMgs1ADeZGNv2DXn3x6+Dth8ePhbrPg2/u2077aEeC+SFZTbyowZSUONyNgpIgKl4
3kTcu7I5q9JVY+ZcJcsrn5xf8MY6fb/thXvwttPEHiSDUZrW41CHxa2jxNNDGLfzLKTYGCm2Rv8A
R5robVuJcW4hhOZm+VfiJ4B8Y/D34na74S1vWF8WeKby/n06f/hHZX1GS9vJnijnYSzJuuZ3k2bo
kPmby6t5TKy16D+01r3xP+HsHhn4MfEe5hl0nwzNNJa2F9Ixilt5AhE1s4G17WNI5I7dmUzRCaeE
AFfLj6DRfD/j/wAE/C/4h+Lte0LxRDb+LtMs0h8VtMV01YL24S8C3VzKjNPBeRBRK8TKfMWOG4G+
4JHjaxVpId42UVH3fy0/DYw/2rv2Ltc/Z48IeBtU1f7dqC+INOikvTJIJ7iw1jyEM2nl1Vo3VriW
WWMo4Lok4KuYRI0v7I/wj0z48eINd8Na38Trf4Z6dNDKukQ380VpfXlzfxtaxpYW+6NHWVIo1uTH
zMnlw4G4SLzfx3Oh6LZJaeF9d8SXl7C1kLq38VWa6OIrmG2a1eAwmaRpJbOWSWKPeYhZpEY1Nysg
lHLfCTVvD8njLw0fE2kXmqaVDcSW+u6Lpck0N5LaExr9hE1xI0aKqxTShV8p2zKnmpmNonzaXY3U
ind7L8PV9Py6H6h6L8E/hZpP7M3jj4OSfEjR/iDr/h833iF7HTL6GG40W4t8KVtrZJZJbJAwKSgN
kvc3GSvnFR734R/aV+CMPgPRbzTPiB4J0Hw+tvDbW1m2tWNtHZYiVktSiybY2RMDyx90DjgV8lfs
/wD7Kf7Ncejald2HxnsPE9rr0c2h6VFa6laWMtl/allJawJJExLtqLwG5QB1RWO8/ZldCR5l4Z/4
J33dj+1fY+D/ABL/AMJLqdi+nS30njvTRb2KzIsQXzo0kjmhVVeSK1a1+afcRcb1iYIMHFbM7eac
EuWC7b/d02/I/TL/AIXF4B/6Hfw3/wCDa3/+Lr8sPGHxQ139qv49aV4U8TWfhf4ZWV14lil1bVNJ
ht4Jma3gmBju9Qk80XcsNiZ47eZFWB2nBxtK7f1q8K+F9M8E+F9H8O6LbfYtG0izh0+ytvMaTyoI
kEcabmJZsKoGWJJxySa8J/ac+Ffws0nxBpPx68dxasb3wVHbrHDprgi/dboPYwshGdy3cqsm14lL
OPOZo1wuUZJOyNMRTdSK1069rdSz8P8A4p+FvhpoGi+GrgzaP4C0zSre30TxZqtvcWdlLbxRHy4p
pbiNFWRYYw28MySBWYFCRGPZdL1Sy13S7PUtNvLfUNOvIUuLa8tZVlhnidQySI6khlZSCCDgggiv
A/jNpN/+29+yzYS/DHW4dJg1a8hupLbXITCJvs07LJayyKkpheK5iV98ayK7WoQFo5C9ZU/iKH9g
H4V+F9D1yC68XeEz/oVrfaRBHHqEuqyma6uRJFLMsYjkP2iZCHAjCGM7jtZvYoYtP3Z6HHWp2vOP
w2vc+m6Ky/CvibTPGvhjSPEWjXP2zR9Ws4b+yufLaPzYJUDxvtYBlyrA4YAjPIFaleqcwUUUUCCi
iigAooooAKKKKACiiigAooooAKKKKACiiigAooooA+MP+Cn3wl0TUvgbqXxTFzLpnjDwhHAun3i7
WjkSa5SFoZFMbnBE7427fnKFjtXjzj/gmb+2Fp+n6fbfCDx94xiW4j+x2PhRdUkEsssrJIZrRbiM
tGIkxAsCykMTKYkLbUjT7m+Lnw4tPi58O9X8I6g0a2GprHHcLMjukkayo7RsI5I3wwUqSrqw3ZBB
FfmX8SP+Ca3xauLPWL/wbNLM50yEtYa/dWSXV3cyJHHdW8JiBi2fug6yyPEcFU2EhpD5mKoupJcq
N6cpRkpRt59PT9Tlv+CgHwu8X+G/2j9W8U+K9F0zTNK1t7tdPbRmW2tdT0+MgvLMYFM3mxrNA0zz
gmSRmWLKJGp5/wD4UDof7O/xq03R/iUNe1b4e+ILC6uNR8RT6PcWN0sE1lNBIxtbhXiaeyuJopy0
TzsuYnQOx2CL9ofxF+0d4B+E48D/ABhj1W68LGKE2l74xsbfVvL1VZluc22oxCRvMaPzo182Rx5T
zx7QBlOf1H9t74reG/hD8OPAdo3h+MaLerqukahq+k2+oX1oqvIbQrLdGSBBGsu1GjhiaJYVUFVz
u4uSS0ZfLFzvffbfpr/X/DHSftLfss6H8ANL8IRz+K9f8ZajqC3VveXF94LOnQ2OkQLb7pbeO4mj
MlzE0rEAOQ4kALQ7AZfsj4PfCX44p8Vvhh/a3xd1K6i0hb6+vLPULPUB9nshPb+farcXkMb6n9p3
xgtOF+yYDR5KJn4i+NP7WniX9oTwv4I0zxnqk+txeG9Sk1C5nsbSG6W8sblNpmu7SOSCL7VaBHCB
VCFbkq0kTKXn4jx58cviV44v57TWPFGsa/aSRwxRaD4j1g3CJaIkhWO7VxEHlVbe3d5FjRJHijmc
GQoxlxbWoc0E3JdtFe3nrqfav7Uv7WP7TsPx+1f4feBNK1DwlJpV08trp+h+Gf7cvNQ0hjGiapJI
0cqNEXBwsSJsaRonLOnH3r8J9U1v4qfBbSLn4jeErfSNU1mweLVdAu4d8MkbFk+eGTJRZo8OYJMt
GJDG5LKxP4h/A39p34h/s9weHNcs/EmrXPh3TJoZ7bw7/bssOn3cInxeQJaFGiUusjKzMhYOWmQs
w3D9nfC/7XHws8Taha6W/iq10TXG0ptWvNK1dhby6YI0L3FtdyZMUN1AqSGW3MnmRiJ2K7VLVjUj
p7q2OqjUU23fS9ulvl+R6vpOk2Wg6XZ6Zplnb6dptnClvbWdpEsUMESKFSNEUAKqqAAoGAAAK89/
aW8K6942+BvizRfDGj6Lr+u3Nun2bT9ftYbm2lKyo7YjmBiaYKrNF5o8sSrEX+UNW/8AC/4seFPj
N4XHiHwdq6axpfnPbO/lSQywyrgmOWKRVkjbDKwV1BKujDKspOzp/irRNX1zVtFsdYsL3WdI8r+0
tOt7pJLiy81S8XnRg7o96gsu4DcBkZFc6unc6tJR0e5+en/BP/8Aay8WX3jaH4Q+M2k8QJLJcx6R
qSy28s1okCyvhmg/dTWbRxqI50ZgJDtUvG6GP9Da/OD4gfHj4e/AHxV8RNJ8EfCDUvBXiHQNc22f
iOOSNII53jmi23jTxS/YbKRDJJaQRBkmXDIsGSR96/CrxNrPjT4c+Hdd8Q6FP4Z1nULNLi50q5Ur
LbswyA6EkxsRgmMklCSpJKk19FhajnGzPElHl63OqoooruICiiigAooooAKKKKACiiigAooooAKK
KKACiiigAooooAKKKKAKuqaXZa7pd5pupWdvqOnXkL29zZ3USywzxOpV43RgQyspIKkYIJBr4C8Z
/wDBG34eat4inuvDfi3VfD2j3LvI+n3UAvZLYlmZUtpfMTagBVcSrMxC/fyc1+g9FRKKluWpOOzP
5zvjX8P9Q/Z1+LHjLwJfJAt7pDnTPMjeWNr63kXzIrsqkrqpkiMTmMuQvmBSpKtjBvPEAHh22XUb
y/u5ryX7WDOqNHPGFClGYP5mDLCF+8BtRWxkAV/Qv8Q/gb8PfixHejxf4L0TxBPeWB0yW8vLKNro
WxYt5aT48yMByXXYwKt8ykNzX5afty/8E8NR+EN1r/jT4daA2p/DKGxF1/ZNvLLPJoTqsUc8r+ZO
ZZFO3zvMUSBR5gkVEiV24alC3vG14Tab3PkHwbealpN7dXdje3NvrEH2VLW2Gpy2l3BepIFhkjIC
5aJ0DgZ+QFfmypr6C/Z/+Muh/AHxpe6jqXw/0Px7pd9ZPozw6xqTw2ulyvbL5sKvLE4kYxNPbys0
JyMRxS+Vu83zhfidf6ZceLdU0s3HhvQdVj1OwvtEtWjhU2dzcw3DaeGggieJVby0crGkZ2CP5Y5S
lfbX/BOf4S6B8ZPgn8R7Cx8T6aNQvCfCmralHp6vrA0aSCNhHAXfbbRyb50DNC5d4WYs/losfmS1
bbMIRnUre7pv3t29L7PX5N6n2L+zv4q+F2i/s53XiT4TaBqEnh60hudRutAs4pLnWmvEiEkltMkr
tJJd7RGiq7ncvkhGMZjNcJ+w74c8FfEG88U/HPRvDereHdd8Q3l5ZyWtzqH2zTV8yZLi6lsJfLja
aOaYIXaQHZNDLHGERCG+PPEuheGP2GfihrTeHfH3iDV/idpunJabrXSkt7S71K6aNY7aWWaaZpIU
tJYro27rsaSEEXUT7Yk+9f2X/E3in47fAvwz411Xxfr2kapfC5gu7W3h00xia3uZbd3UG0O1XaEu
E3PtDbd743HBxVr3PQpyU3FStePQ8qtv2vofiN+3jpvw3sbBLzw5od3qOixXSfaYm/tSKyeW4uHJ
AjcRiKe1WIqT87yiQqyrX2LXzx8H/hv4B+G37S/xUubU2EnjjW/sUkuoTeTFd3AeEyzRrEkMShyy
iaVoQVk3RM/7xWJ+h6+gwsVGmrHJWv7R3YUUUV1mAUUUUAFFFFABRRRQAUUUUAFFFFABRRRQAUUU
UAFFFFABRRRQAUUUUAFZfirwzpnjbwvrHh3Wrb7bo+r2c1he23mNH5sEqGORNykMuVYjKkEZ4INa
lFAz+cTVvC974H8Y3egXWjyeGfEugzNYazBJG16YdgaOebgtGyEMcjlcBCjEMSPpL9kP9o+y/Zz+
MWp+MbvwSdSj8QaXFG6LeOLm0imnV3ismaSQzgrCgjgnJkYxD99H+88z9S/HX7JHwj+JXxEXxz4k
8F2uo+J/Liimu/tE8SXaRkFFuIUkWO4GAqkSq+5FVGyqhRsfC/8AZz+GfwW1TVtS8EeCtJ8O6jqk
001zeWsGZsSMjPEjtkxw7o0IgQrEpUFUFebLCOT30L5rS5ovU/K79rzWvjZ+19K2pD4SxNaaFdyW
cd14U8NS3960quStlJfp5jTxRJJI4kh2W8jSFtpJj29d+w38WP2h/AHw8tdV8EfDdvE3gLXtYjia
O5scm6vUVIna3lidDbROkawtcSxvbQtbrk7jID+tNFX9Ui42bKdR79e58NfDH4dftLfET9oTRta+
L1hZ6f4V0ucag00aaUNskbSvHb2kluHujEJWiKrO2PLExc+bsNfctFFdVOmqasjOUnLcKKKK1JCi
iigAooooA//Z</Data></Thumbnail></Binary></metadata>
